Libreria_AG/__init__.py
Libreria_AG/libreria_ag.py
Libreria_AG/config/__init__.py
Libreria_AG/config/default_parameters.py
Libreria_AG/core/__init__.py
Libreria_AG/core/population.py
Libreria_AG/operators/__init__.py
Libreria_AG/operators/crossover.py
Libreria_AG/operators/fitness.py
Libreria_AG/operators/mutation.py
Libreria_AG/operators/selection.py
Libreria_AG-0.2.dist-info/METADATA
Libreria_AG-0.2.dist-info/WHEEL
Libreria_AG-0.2.dist-info/top_level.txt
Libreria_AG-0.2.dist-info/RECORD
